stonks_trader/__init__.py
stonks_trader/cli/__init__.py
stonks_trader/cli/cli_app.py
stonks_trader/helpers/__init__.py
stonks_trader/helpers/indicator_utils.py
stonks_trader/trade_strategies/__init__.py
stonks_trader/trade_strategies/bollinger.py
stonks_trader/trade_strategies/compression.py
stonks_trader/trade_strategies/macd.py
stonks_trader/trade_strategies/rsi.py
stonks_trader/trade_strategies/sma.py
stonks_trader/trade_strategies/stochastic.py
stonks_trader/trade_strategies/strategy.py
stonks_trader-0.2.3.dist-info/entry_points.txt
stonks_trader-0.2.3.dist-info/WHEEL
stonks_trader-0.2.3.dist-info/METADATA
stonks_trader-0.2.3.dist-info/RECORD
