Metadata-Version: 2.1
Name: stonks-trader
Version: 0.2.3
Summary: 
Author: glyphack
Author-email: sh.hooshyari@gmail.com
Requires-Python: >=3.8,<4.0
Classifier: Programming Language :: Python :: 3
Classifier: Programming Language :: Python :: 3.8
Requires-Dist: click-spinner (==0.1.10)
Requires-Dist: matplotlib
Requires-Dist: numpy
Requires-Dist: pandas
Requires-Dist: pandas-ta (==0.1.39b)
Requires-Dist: pytse_client
Requires-Dist: requests
Requires-Dist: ta
Requires-Dist: typer
